{
  "_comment": "Override auto-generated slugs to use English IDs internally for database entries and filenames.",
  "aniol": "angel",
  "czlowiek": "human",
  "magiczny-pocisk": "magic-missile",
  "magiczna-tarcza": "magic-shield",
  "poblask": "gleam",
  "telekineza": "telekinesis",
  "przeskok": "blink",
  "teleportacja": "teleport",
  "przebicie-eteru": "ether-pierce",
  "fala-energii": "energy-wave",
  "przeblysk-prawdy": "truth-glimpse",
  "szybka-mysl": "quick-thought",
  "latanie": "flight",
  "powietrzna-fala": "air-wave",
  "wyczucie-zagrozenia": "danger-sense",
  "celnosc": "accuracy",
  "szybki-jak-wiatr": "wind-swift",
  "tworzenie-i-kontrolowanie-wody": "water-create",
  "lodowa-podloga": "ice-floor",
  "ukojenie": "solace",
  "gradobicie": "hailstorm",
  "mistyczna-mgla": "mystic-fog",
  "podpalenie": "ignition",
  "wzniecanie-ognia": "kindle",
  "ognista-powloka": "fire-cloak",
  "kula-ognia": "fireball",
  "gorejaca-skora": "burning-skin",
  "skalista-tarcza": "stone-shield",
  "ruchome-piaski": "quicksand",
  "trzesienie-ziemi": "earthquake",
  "zwirowa-zbroja": "gravel-armor",
  "skalista-pulapka": "stone-trap",
  "eteryczny-przewodnik": "ether-guide",
  "labirynt-umyslu": "mind-labyrinth",
  "madrosc-salomona": "wisdom-of-solomon",
  "magiczna-odpornosc": "magic-resistance",
  "magiczne-kajdany": "magic-shackles",
  "magnetyzm": "magnetism",
  "negacja": "negation",
  "niewidzialnosc": "invisibility",
  "ozywienie-szkieletu": "animate-skeleton",
  "przemiana-w-olow": "lead-transmutation",
  "rozmawianie-ze-zmarlymi": "speak-with-dead",
  "rozsypanie": "shatter",
  "uzdrowienie-chorych": "heal-sick",
  "woal-snow": "dream-veil",
  "wymagania-rasa-czlowiek": "requirements-race-human",
  "zloto-glupcow": "fools-gold",
  "zwierciadlany-wizerunek": "mirror-image",
  "blogoslawienstwo-zasiewow": "sowing-blessing",
  "blyskawice-lancuchowe": "chain-lightning",
  "boska-celnosc": "divine-accuracy",
  "boska-sprawiedliwosc": "divine-justice",
  "boska-wlocznia": "divine-spear",
  "chmara-insektow": "insect-swarm",
  "cykl-por-roku": "seasons-cycle",
  "egida": "aegis",
  "gniew-matki-ziemi": "wrath-of-mother-earth",
  "grom-z-nieba": "thunderbolt",
  "klatwa-hekate": "curse-of-hekate",
  "kradziez-many": "mana-drain",
  "leczacy-dotyk": "healing-touch",
  "magiczne-przyspieszenie": "magic-haste",
  "moc-ziemi": "earth-power",
  "modlitwa-o-opieke": "prayer-for-protection",
  "obecnosc-krola-bogow": "presence-of-the-king-of-gods",
  "piekno-bogini": "beauty-of-the-goddess",
  "plomien-namietnosci": "flame-of-passion",
  "pomost": "bridge",
  "pozadanie-zmyslow": "senses-desire",
  "promien-harmonii": "ray-of-harmony",
  "przebudzenie": "awakening",
  "przyspieszone-zniwa": "accelerated-harvest",
  "sad-ostateczny": "last-judgment",
  "strzala-kupidyna": "cupids-arrow",
  "strzala-pozadania": "arrow-of-desire",
  "swieta-stal": "holy-steel",
  "tajemne-poznanie": "arcane-cognition",
  "tesknota-serca": "heart-longing",
  "urok-niewinnosci": "charm-of-innocence",
  "uswiecenie": "sanctification",
  "wiez-serc": "bond-of-hearts",
  "wyladowanie-elektrostatyczne": "electrostatic-discharge",
  "wymagania-rasa-aniol": "requirements-race-angel",
  "wzmocnienie-magii": "magic-empowerment",
  "neutralizacja": "neutralization",
  "pierwotna-kula": "primal-orb",
  "tajemniczy-strumien": "mysterious-stream",
  "zakazana-oslona": "forbidden-shield",
  "klatwa-szkarlatu": "crimson-curse",
  "szkarlatna-sprawiedliwosc": "crimson-justice",
  "szkarlatne-plomienie": "crimson-flames",
  "szkarlatny-pocisk": "crimson-bolt",
  "szkarlatny-sztylet": "crimson-dagger",
  "superzaklecie-requiem": "superspell-requiem",
  "arcymag-dziedzina": "archmage",
  "blogoslawienstwo-bostwo": "deity-blessing",
  "blogoslawione-pochodzenie": "blessed-origin",
  "cios-w-plecy": "backstab",
  "czuly-zmysl": "keen-sense",
  "czuly-zmysl-zmysl": "keen-sense",
  "darmowy-talent": "free-talent",
  "dyplomata": "diplomat",
  "finta": "feint",
  "gadanina": "babble",
  "gotowosc-do-walki": "battle-readiness",
  "jednosc-z-magia": "unity-with-magic",
  "jednosc-z-natura": "unity-with-nature",
  "magiczna-dyscyplina": "magic-discipline",
  "magiczny-zmysl-zmysl": "magical-sense",
  "mistrz-magii-dziedzina": "master-of-magic",
  "niezniszczalne-zaklecia": "indestructible-spells",
  "obureczny": "ambidextrous",
  "odpornosc-na-magie": "magic-resistance",
  "odpornosc-na-trucizny": "poison-resistance",
  "oportunista": "opportunist",
  "pancerz-wiary": "armor-of-faith",
  "parowanie": "parry",
  "powietrzne-uniki": "air-evasion",
  "riposta": "riposte",
  "rozplatanie-zaklec": "spell-shattering",
  "sen-na-jawie": "daydream",
  "technologia-jest-wsrod-nas": "technology-is-among-us",
  "urok-osobisty": "personal-charm",
  "zakazana-wiedza-dziedzina": "forbidden-knowledge",
  "zawisanie-w-powietrzu": "levitation",
  "medyk-polowy": "field-medic",
  "olimpijczyk": "olympian",
  "czlowiek-z-zelaza": "man-of-iron",
  "pasjonat-zwierzat": "animal-enthusiast",
  "jestes-magiem-krwi-i-rozumiesz-jak-cenne-jest-zycie": "blood-mage-precious-life",
  "oltarz-krwi": "blood-altar",
  "szacunek-do-zycia": "respect-for-life",
  "dar-otchlani": "gift-of-the-abyss",
  "magowie-aspektow-moga-sie-ukrywac-jako-magowie-swojej-pierwotnej-dziedziny": "aspect-mages-disguise",
  "metamagia": "metamagic",
  "swobodny-przeplyw-magii": "free-flow-of-magic",
  "gear-bicz": "whip",
  "gear-bron-dwureczna": "two-handed-weapon",
  "gear-bron-jednoreczna-lub-poltorareczna": "one-handed-or-bastard-weapon",
  "gear-laska-quarterstaff": "quarterstaff",
  "gear-luk-bloczkowy": "compound-bow",
  "gear-luk-elfi": "elven-bow",
  "gear-luk-klasyczny": "classic-bow",
  "gear-sztylet": "dagger",
  "gear-wlocznia": "spear",
  "gear-pancerz-ciezki": "heavy-armor",
  "gear-pancerz-lekki": "light-armor",
  "gear-pancerz-sredni": "medium-armor",
  "gear-tarcza": "shield",
  "gear-artefakt-przechowujacy-mane": "mana-storage-artifact",
  "gear-artefakt-skupiajacy-magie": "magic-focus-artifact",
  "gear-karty-do-gry": "playing-cards",
  "gear-kociolek": "cauldron",
  "gear-miecz-swietlny": "lightsaber",
  "gear-miecz-treningowy": "training-sword",
  "gear-przedmioty-do-wrozenia": "divination-tools",
  "gear-przybory-do-golemancji": "golemancy-tools",
  "gear-przybory-do-tworzenia-artefatow": "artifact-crafting-tools",
  "gear-shinai": "shinai",
  "gear-szklana-fiolka": "glass-vial",
  "gear-tablica-ouija": "ouija-board",
  "gear-teleskop": "telescope",
  "gear-zestaw-do-rytualow": "ritual-kit",
  "ostrze-dawida": "blade-of-david",
  "fanatyczne-poswiecenie": "fanatical-sacrifice",
  "wykrycie-zmian": "detect-changes",
  "destrukcja": "destruction",
  "prawdziwa-dezintegracja": "true-disintegration",
  "zaglada": "doom",
  "magiczna-plaga": "magic-plague",
  "aegis": "aegis",
  "transmutacja-krajobrazu": "landscape-transmutation",
  "bramy-wymiarow": "dimension-gates",
  "reanimacja": "reanimation",
  "plomienna-strzala": "flaming-arrow",
  "tarcza-eteryczna": "ethereal-shield",
  "echo-zmierzchu": "twilight-echo",
  "requiem": "requiem",
  "przywolanie-istoty-z-otchlani": "summon-eldritch-entity",
  "nic-przeznaczenia": "thread-of-destiny",
  "naturalny-lot": "natural-flight"
}